odoo10_addon_invader_payment_stripe-10.0.2.0.0-py3.8-nspkg.pth
odoo/addons/invader_payment_stripe/README.rst
odoo/addons/invader_payment_stripe/__init__.py
odoo/addons/invader_payment_stripe/__manifest__.py
odoo/addons/invader_payment_stripe/demo/payment_demo.xml
odoo/addons/invader_payment_stripe/readme/CONTRIBUTORS.rst
odoo/addons/invader_payment_stripe/readme/DESCRIPTION.rst
odoo/addons/invader_payment_stripe/services/__init__.py
odoo/addons/invader_payment_stripe/services/payment_stripe.py
odoo/addons/invader_payment_stripe/static/description/icon.png
odoo/addons/invader_payment_stripe/static/description/index.html
odoo10_addon_invader_payment_stripe-10.0.2.0.0.dist-info/METADATA
odoo10_addon_invader_payment_stripe-10.0.2.0.0.dist-info/WHEEL
odoo10_addon_invader_payment_stripe-10.0.2.0.0.dist-info/namespace_packages.txt
odoo10_addon_invader_payment_stripe-10.0.2.0.0.dist-info/top_level.txt
odoo10_addon_invader_payment_stripe-10.0.2.0.0.dist-info/RECORD
